wicc/__init__.py
wicc/serializer.py
wicc/transactions.py
wicc/wallet.py
wicc/baas/__init__.py
wicc/baas/manager.py
wicc/cryptos/__init__.py
wicc/cryptos/blocks.py
wicc/cryptos/composite.py
wicc/cryptos/constants.py
wicc/cryptos/deterministic.py
wicc/cryptos/keystore.py
wicc/cryptos/main.py
wicc/cryptos/mnemonic.py
wicc/cryptos/py2specials.py
wicc/cryptos/py3specials.py
wicc/cryptos/ripemd.py
wicc/cryptos/segwit_addr.py
wicc/cryptos/stealth.py
wicc/cryptos/transaction.py
wicc/cryptos/wallet.py
wicc/cryptos/wallet_utils.py
wicc/cryptos/words.py
wicc/cryptos/coins/__init__.py
wicc/cryptos/coins/base.py
wicc/cryptos/coins/bitcoin.py
wicc/cryptos/coins/bitcoin_cash.py
wicc/cryptos/coins/bitcoin_gold.py
wicc/cryptos/coins/dash.py
wicc/cryptos/coins/dogecoin.py
wicc/cryptos/coins/litecoin.py
wicc/cryptos/coins/waykicoin.py
wicc/cryptos/electrumx_client/__init__.py
wicc/cryptos/electrumx_client/jsonrpc.py
wicc/cryptos/electrumx_client/rpc.py
wicc/cryptos/electrumx_client/test.py
wicc/cryptos/electrumx_client/util.py
wicc/cryptos/explorers/__init__.py
wicc/cryptos/explorers/base_insight.py
wicc/cryptos/explorers/bitpay.py
wicc/cryptos/explorers/blockchain.py
wicc/cryptos/explorers/blockcypher.py
wicc/cryptos/explorers/blockdozer.py
wicc/cryptos/explorers/btg_explorer.py
wicc/cryptos/explorers/dash_siampm.py
wicc/cryptos/explorers/sochain.py
wicc/cryptos/explorers/utils.py
wicc/wiccrpc/__init__.py
wicc/wiccrpc/account.py
wicc/wiccrpc/block.py
wicc/wiccrpc/contract.py
wicc/wiccrpc/node.py
wicc/wiccrpc/transaction.py
wicc/wiccrpc/vote.py
wicc/wiccrpc/wallet.py
wicc/wiccrpc/box/Config.py
wicc/wiccrpc/box/RpcManager.py
wicc/wiccrpc/box/__init__.py
wicc_wallet_utils-1.0.1.dist-info/LICENSE
wicc_wallet_utils-1.0.1.dist-info/METADATA
wicc_wallet_utils-1.0.1.dist-info/WHEEL
wicc_wallet_utils-1.0.1.dist-info/top_level.txt
wicc_wallet_utils-1.0.1.dist-info/RECORD
