Metadata-Version: 2.1
Name: wicc-wallet-utils
Version: 1.0.1
Summary: WaykiChain Wallet Utils
Home-page: https://github.com/WaykiChain/wicc-wallet-utils-python
Author: WaykiChain CoreDev
Author-email: coredev@waykichainhk.com
License: UNKNOWN
Platform: UNKNOWN
Classifier: Programming Language :: Python :: 3
Classifier: License :: OSI Approved :: MIT License
Classifier: Operating System :: OS Independent
Requires-Dist: cryptos (==1.36)
Requires-Dist: requests
Requires-Dist: pbkdf2
